{
  "study_id": "study_1",
  "study_info": {
    "title": "Medullary Thyroid Carcinoma and Clinical Outcomes in Heterozygous Carriers of the RET K666N Germline Pathogenic Variant",
    "journal": "JCEM Case Reports",
    "publication_date": "March 2025",
    "study_type": "Case series"
  },
  "patient_data": [
    {
      "patient_id": "Patient_1_Proband",
      "age": 24,
      "gender": "Female",
      "relationship": "Proband",
      "ret_variant": "K666N",
      "ret_status": "Positive",
      "calcitonin_level": "Undetectable",
      "calcitonin_normal_range": "0.0-7.5 pg/mL",
      "thyroid_ultrasound": "Normal",
      "mtc_diagnosis": "No",
      "pheochromocytoma": "No",
      "hyperparathyroidism": "No",
      "men2_syndrome": "No",
      "genetic_testing_reason": "Breast cancer risk stratification"
    },
    {
      "patient_id": "Patient_2_Sister",
      "age": 21,
      "gender": "Female",
      "relationship": "Sister",
      "ret_variant": "K666N",
      "ret_status": "Positive",
      "calcitonin_level": "Undetectable",
      "calcitonin_normal_range": "0.0-7.5 pg/mL",
      "thyroid_ultrasound": "Normal",
      "mtc_diagnosis": "No",
      "pheochromocytoma": "No",
      "hyperparathyroidism": "No",
      "men2_syndrome": "No",
      "genetic_testing_reason": "Family screening"
    },
    {
      "patient_id": "Patient_3_Father",
      "age": 60,
      "gender": "Male",
      "relationship": "Father",
      "ret_variant": "K666N",
      "ret_status": "Positive",
      "calcitonin_level": "13 pg/mL",
      "calcitonin_normal_range": "0.0-7.5 pg/mL",
      "calcitonin_elevated": "Yes",
      "thyroid_ultrasound": "Multiple subcentimeter solid hypoechoic nodules",
      "thyroid_nodule_count": 3,
      "largest_nodule_size_mm": 6,
      "biopsy_result": "Bethesda V - Suspicious for malignancy",
      "mtc_diagnosis": "Yes",
      "mtc_stage": "pT1aNxMx",
      "mtc_size_mm": 8,
      "mtc_bilateral": "Yes",
      "c_cell_hyperplasia": "Yes",
      "treatment": "Total thyroidectomy",
      "postop_calcitonin": "Undetectable",
      "pheochromocytoma": "No",
      "hyperparathyroidism": "No",
      "men2_syndrome": "No",
      "family_screening": "Yes"
    },
    {
      "patient_id": "Patient_4_Grandmother",
      "age": 84,
      "gender": "Female",
      "relationship": "Paternal grandmother",
      "ret_variant": "K666N",
      "ret_status": "Positive",
      "calcitonin_level": "37 pg/mL",
      "calcitonin_normal_range": "0.0-7.5 pg/mL",
      "calcitonin_elevated": "Yes",
      "thyroid_ultrasound": "Multiple thyroid nodules",
      "mtc_diagnosis": "Suspected (declined workup)",
      "c_cell_disease_suspected": "Yes",
      "pheochromocytoma": "No",
      "hyperparathyroidism": "No",
      "men2_syndrome": "No",
      "declined_further_evaluation": "Yes"
    }
  ]
}
